setup.py
distributions/Binomialdistribution.py
distributions/Gaussiandistribution.py
distributions/Generaldistribution.py
distributions/__init__.py
erens_distributions.egg-info/PKG-INFO
erens_distributions.egg-info/SOURCES.txt
erens_distributions.egg-info/dependency_links.txt
erens_distributions.egg-info/not-zip-safe
erens_distributions.egg-info/top_level.txt